imbaedit/__init__.py
imbaedit/imbaedit.py
imbaedit-1.0.5.dist-info/METADATA
imbaedit-1.0.5.dist-info/WHEEL
imbaedit-1.0.5.dist-info/entry_points.txt
imbaedit-1.0.5.dist-info/top_level.txt
imbaedit-1.0.5.dist-info/RECORD
