Metadata-Version: 2.1
Name: imbaedit
Version: 1.0.5
Summary: Image Batch Editor
Home-page: https://github.com/jncraton/imbaedit
Author: Jon Craton
Author-email: jon@joncraton.com
License: UNKNOWN
Platform: UNKNOWN
Classifier: Programming Language :: Python :: 3
Classifier: License :: OSI Approved :: MIT License
Classifier: Operating System :: OS Independent
Requires-Python: >=3.6
Requires-Dist: pillow
